Metadata-Version: 2.4
Name: adafruit-circuitpython-stspin
Version: 1.0.1
Summary: CircuitPython driver for the Adafruit STSPIN220 Stepper Motor Driver Breakout Board
Author-email: Adafruit Industries <circuitpython@adafruit.com>
License: MIT
Project-URL: Homepage, https://github.com/adafruit/Adafruit_CircuitPython_STSPIN
Keywords: adafruit,blinka,circuitpython,micropython,stspin,stepper,motor,,STSPIN220
Classifier: Intended Audience :: Developers
Classifier: Topic :: Software Development :: Libraries
Classifier: Topic :: Software Development :: Embedded Systems
Classifier: Topic :: System :: Hardware
Classifier: License :: OSI Approved :: MIT License
Classifier: Programming Language :: Python :: 3
License-File: LICENSE
Requires-Dist: Adafruit-Blinka
Provides-Extra: optional
Dynamic: license-file
